{
	"key_items_grid": {
		"type": "array",
		"orientation": "horizontal",
		"margin": "0,0",
		"content": [
			{
				"type": "itemgrid",
				"item_margin": "2,2",
				"h_alignment": "left",
				"item_h_alignment": "center",
				"item_v_alignment": "center",
				"item_height": 36,
				"item_width": 36,
				"rows": [
					[
						"CoalBadge",
						"ForestBadge",
						"CobbleBadge",
						"FenBadge",
						"RelicBadge",
						"MineBadge",
						"IcicleBadge",
						"BeaconBadge"
					],
					[
						"HM01Cut",
						"HM02Fly",
						"HM03Surf",
						"HM04Strength",
						"HM05Defog",
						"HM06RockSmash",
						"HM07Waterfall",
						"HM08RockClimb"
					],
					[
						"TM70-Flash",
						"Bicycle",
						"SecretPotion",
						"S.S.Ticket",
						"Parcel",
						"OldCharm",
						"none",
						"azureflute"
					],
					[
						"Coupon1",
						"Coupon2",
						"Coupon3",
						"GalacticKey",
						"WorksKey",
						"SuiteKey",
						"StorageKey",
						"oaksletter"
					],
					[
						"Poketch",
						"DowsingMachineApp",
						"ProgressivePokedex",
						"Pachirisu",
						"Snorlax",
						"KEcleon",
						"SuperRod",
						"membercard"
					]
				]
			}
		]
	},
	"poketch_apps_grid": {
		"type": "array",
		"orientation": "horizontal",
		"margin": "0,0",
		"content": [
			{
				"type": "itemgrid",
				"item_margin": "2,2",
				"h_alignment": "left",
				"item_h_alignment": "center",
				"item_v_alignment": "center",
				"item_height": 36,
				"item_width": 36,
				"rows": [
					[
						"DigitalWatchApp",
						"CalculatorApp",
						"MemoPadApp",
						"PedometerApp",
						"PokemonListApp",
						"FriendshipCheckerApp"
					],
					[
						"StopwatchApp",
						"BerrySearcherApp",
						"Day-CareCheckerApp",
						"PokemonHistoryApp",
						"CounterApp",
						"AnalogWatchApp"
					],
					[
						"MarkingMapApp",
						"LinkSearcherApp",
						"CoinTossApp",
						"MoveTesterApp",
						"CalendarApp",
						"DotArtistApp"
					],
					[
						"RouletteApp",
						"ChainCounterApp",
						"KitchenTimerApp",
						"ColorChangerApp",
						"MatchupCheckerApp",
						"AlarmClockApp"
					]
				]
			}
		]
	},
	"plates_grid": {
		"type": "array",
		"orientation": "horizontal",
		"margin": "0,0",
		"content": [
			{
				"type": "itemgrid",
				"item_margin": "2,2",
				"h_alignment": "left",
				"item_h_alignment": "center",
				"item_v_alignment": "center",
				"item_height": 36,
				"item_width": 36,
				"rows": [
					[
						"FistPlate",
						"SkyPlate",
						"ToxicPlate",
						"EarthPlate"
					],
					[
						"StonePlate",
						"InsectPlate",
						"SpookyPlate",
						"IronPlate"
					],
					[
						"ZapPlate",
						"FlamePlate",
						"SplashPlate",
						"MeadowPlate"
					],
					[
						"MindPlate",
						"IciclePlate",
						"DracoPlate",
						"DreadPlate"
					]
				]
			}
		]
	},
	"events_grid": {
		"type": "array",
		"orientation": "vertical",
		"margin": "0,0",
		"content": [
			{
				"type": "itemgrid",
				"item_margin": "2,2",
				"h_alignment": "left",
				"item_h_alignment": "center",
				"item_v_alignment": "center",
				"item_height": 36,
				"item_width": 36,
				"rows": [
					[
						"event_oreburgh",
						"event_veilstone",
						"event_pastoria",
						"event_canalave",
						"event_palpark"
					],
					[
						"event_warehouse",
						"event_saturn",
						"event_mars",
						"event_jupiter",
						"event_galactichq"
					],
					[
						"event_bombs",
						"event_guardians",
						"event_distortion",
						"event_arceus",
						"event_cynthia"
					]
				]
			}
		]
	},
	"settings_grid": {
		"type": "array",
		"orientation": "vertical",
		"margin": "0,0",
		"content": [
			{
				"type": "itemgrid",
				"item_margin": "2,2",
				"h_alignment": "left",
				"item_h_alignment": "center",
				"item_v_alignment": "center",
				"item_height": 36,
				"item_width": 36,
				"rows": [
					[
						"opt_hidden",
						"opt_dowsing",
						"opt_217",
						"opt_bz",
						"opt_victory"
					],
					[
						"opt_flash",
						"opt_fly_north",
						"opt_fly_early",
						"opt_defog_cross",
						"opt_defog_items",
					],
					[
						"opt_open_sshore",
						"opt_extra_blocks",
						"opt_skey",
						"funny",
						"event_toggle"
					]
				]
			}
		]
	}
}
